{
  "Name": "Deck",
  "Transform": {
    "posX": 36.9486,
    "posY": 2.4263,
    "posZ": 31.4403,
    "rotX": 0.0,
    "rotY": 180.0,
    "rotZ": 0.0,
    "scaleX": 1.0,
    "scaleY": 1.0,
    "scaleZ": 1.0
  },
  "Nickname": "General Set",
  "Description": "",
  "GMNotes": "",
  "AltLookAngle": {
    "x": 0.0,
    "y": 0.0,
    "z": 0.0
  },
  "ColorDiffuse": {
    "r": 0.7132,
    "g": 0.7132,
    "b": 0.7132
  },
  "Tags": [
    "Path"
  ],
  "LayoutGroupSortIndex": 0,
  "Value": 0,
  "Locked": false,
  "Grid": false,
  "Snap": true,
  "IgnoreFoW": false,
  "MeasureMovement": false,
  "DragSelectable": true,
  "Autoraise": true,
  "Sticky": true,
  "Tooltip": true,
  "GridProjection": false,
  "HideWhenFaceDown": false,
  "Hands": false,
  "SidewaysCard": false,
  "DeckIDs": [
    1461,
    1460,
    1459,
    1459,
    1458,
    1458,
    1457,
    1456,
    1456,
    1456,
    1456,
    1456,
    1455,
    1454,
    1453
  ],
  "CustomDeck": {
    "14": {
      "FaceURL": "https://steamusercontent-a.akamaihd.net/ugc/14171969799069107/6224D5616F8250C34631EDE0759ECD1C8F47BCE2/",
      "BackURL": "https://steamusercontent-a.akamaihd.net/ugc/14171969799074052/780A3D85AC2356930B95B87A12824F954C477092/",
      "NumWidth": 9,
      "NumHeight": 7,
      "BackIsHidden": false,
      "UniqueBack": false,
      "Type": 0
    }
  }
}
